{
  "id": {
    "checks": {
      "type": "string",
      "required": false
    },
    "resets": {
      "trim": " ",
      "removeMultipleSpaces": true
    },
    "name": "id",
    "alias": "id",
    "entityName": "resolucion",
    "refEntityName": null,
    "refFieldName": null,
    "dataType": "string",
    "notNull": false,
    "defaultValue": null
  },
  "numero": {
    "checks": {
      "type": "string",
      "required": false
    },
    "resets": {
      "trim": " ",
      "removeMultipleSpaces": true
    },
    "name": "numero",
    "alias": "num",
    "entityName": "resolucion",
    "refEntityName": null,
    "refFieldName": null,
    "dataType": "string",
    "notNull": false,
    "defaultValue": null
  },
  "anio": {
    "checks": {
      "type": "year",
      "required": true
    },
    "resets": {},
    "name": "anio",
    "alias": "ani",
    "entityName": "resolucion",
    "refEntityName": null,
    "refFieldName": null,
    "dataType": "year",
    "notNull": true,
    "defaultValue": "NULL"
  },
  "tipo": {
    "checks": {
      "type": "string",
      "required": true
    },
    "resets": {
      "trim": " ",
      "removeMultipleSpaces": true
    },
    "name": "tipo",
    "alias": "tip",
    "entityName": "resolucion",
    "refEntityName": null,
    "refFieldName": null,
    "dataType": "string",
    "notNull": true,
    "defaultValue": "NULL"
  }
}