{
    "CANT": {
        "alias": "CAN",
        "dataType": "float"
    },

    "CANT_ENTRE": {
        "alias": "CA1",
        "dataType": "float",
        "defaultValue": "(0)"
    },

    "CODPROD": {
        "alias": "COD",
        "dataType": "int",
        "refEntityName": "CODPROD"
    },

    "DJPROD": {
        "alias": "DJP",
        "dataType": "string",
        "refEntityName": "DTOJUD"
    },

    "DTOJUD": {
        "alias": "DTO",
        "dataType": "string",
        "refEntityName": "DTOJUD"
    },

    "ESTADO": {
        "alias": "EST",
        "dataType": "string",
        "refEntityName": "REFERENCIA"
    },

    "FECHA_PEDIDO": {
        "alias": "FEC",
        "dataType": "DateTime",
        "refEntityName": "FECHA_PEDIDO"
    },

    "FLISTA": {
        "alias": "FLI",
        "dataType": "bool"
    },

    "ITEM": {
        "alias": "ITE",
        "dataType": "int"
    },

    "MARCA1": {
        "alias": "MAR",
        "dataType": "int"
    },

    "MARCA2": {
        "alias": "MA1",
        "dataType": "int"
    },

    "MARCA3": {
        "alias": "MA2",
        "dataType": "int"
    },

    "NROPED": {
        "alias": "NRO",
        "dataType": "int",
        "refEntityName": "NROPED"
    },

    "O_SIMILAR": {
        "alias": "O_S",
        "dataType": "bool",
        "defaultValue": "(1)"
    },

    "OBSITEM": {
        "alias": "OBS",
        "dataType": "string"
    },

    "PRODFLISTA": {
        "alias": "PRO",
        "dataType": "string"
    },

    "SERIEPED": {
        "alias": "SER",
        "dataType": "string",
        "refEntityName": "SERIEPED"
    }

}